{
  "openapi": "3.0.1",
  "info": {
    "title": "ASP.NET 8 Web API",
    "description": "ITI Project",
    "version": "v1"
  },
  "paths": {
    "/api/Admin": {
      "get": {
        "tags": [
          "Admin"
        ],
        "responses": {
          "200": {
            "description": "OK"
          }
        }
      }
    },
    "/api/Admin/accept-vendor{vendorId}-{AdminId}": {
      "put": {
        "tags": [
          "Admin"
        ],
        "parameters": [
          {
            "name": "vendorId",
            "in": "path",
            "required": true,
            "schema": {
              "type": "integer",
              "format": "int32"
            }
          },
          {
            "name": "AdminId",
            "in": "path",
            "required": true,
            "schema": {
              "type": "integer",
              "format": "int32"
            }
          }
        ],
        "responses": {
          "200": {
            "description": "OK"
          }
        }
      }
    },
    "/api/Admin/reject-vendor{vendorId}": {
      "put": {
        "tags": [
          "Admin"
        ],
        "parameters": [
          {
            "name": "vendorId",
            "in": "path",
            "required": true,
            "schema": {
              "type": "integer",
              "format": "int32"
            }
          },
          {
            "name": "AdminId",
            "in": "query",
            "schema": {
              "type": "integer",
              "format": "int32"
            }
          }
        ],
        "responses": {
          "200": {
            "description": "OK"
          }
        }
      }
    },
    "/api/Admin/posts": {
      "get": {
        "tags": [
          "Admin"
        ],
        "responses": {
          "200": {
            "description": "OK"
          }
        }
      }
    },
    "/api/Admin/accept-post{postId}": {
      "put": {
        "tags": [
          "Admin"
        ],
        "parameters": [
          {
            "name": "postId",
            "in": "path",
            "required": true,
            "schema": {
              "type": "integer",
              "format": "int32"
            }
          }
        ],
        "responses": {
          "200": {
            "description": "OK"
          }
        }
      }
    },
    "/api/Admin/reject-post{postId}": {
      "put": {
        "tags": [
          "Admin"
        ],
        "parameters": [
          {
            "name": "postId",
            "in": "path",
            "required": true,
            "schema": {
              "type": "integer",
              "format": "int32"
            }
          }
        ],
        "responses": {
          "200": {
            "description": "OK"
          }
        }
      }
    },
    "/api/Admin/EnableAutoPost": {
      "put": {
        "tags": [
          "Admin"
        ],
        "requestBody": {
          "content": {
            "application/json": {
              "schema": {
                "$ref": "#/components/schemas/GrantPermissionDto"
              }
            },
            "text/json": {
              "schema": {
                "$ref": "#/components/schemas/GrantPermissionDto"
              }
            },
            "application/*+json": {
              "schema": {
                "$ref": "#/components/schemas/GrantPermissionDto"
              }
            }
          }
        },
        "responses": {
          "200": {
            "description": "OK"
          }
        }
      }
    },
    "/api/Product/add": {
      "post": {
        "tags": [
          "Product"
        ],
        "requestBody": {
          "content": {
            "multipart/form-data": {
              "schema": {
                "type": "object",
                "properties": {
                  "ProductId": {
                    "type": "integer",
                    "format": "int32"
                  },
                  "Name": {
                    "type": "string"
                  },
                  "Price": {
                    "type": "number",
                    "format": "double"
                  },
                  "ImageFile": {
                    "type": "string",
                    "format": "binary"
                  },
                  "Description": {
                    "type": "string"
                  },
                  "Quantity": {
                    "type": "integer",
                    "format": "int32"
                  },
                  "CategoryName": {
                    "type": "string"
                  },
                  "ImageUrl": {
                    "type": "string"
                  },
                  "NumberOfViewers": {
                    "type": "integer",
                    "format": "int32"
                  },
                  "VendorName": {
                    "type": "string"
                  }
                }
              },
              "encoding": {
                "ProductId": {
                  "style": "form"
                },
                "Name": {
                  "style": "form"
                },
                "Price": {
                  "style": "form"
                },
                "ImageFile": {
                  "style": "form"
                },
                "Description": {
                  "style": "form"
                },
                "Quantity": {
                  "style": "form"
                },
                "CategoryName": {
                  "style": "form"
                },
                "ImageUrl": {
                  "style": "form"
                },
                "NumberOfViewers": {
                  "style": "form"
                },
                "VendorName": {
                  "style": "form"
                }
              }
            }
          }
        },
        "responses": {
          "200": {
            "description": "OK"
          }
        }
      }
    },
    "/api/Product/posts": {
      "get": {
        "tags": [
          "Product"
        ],
        "responses": {
          "200": {
            "description": "OK"
          }
        }
      }
    },
    "/api/Product/ProductVendor": {
      "get": {
        "tags": [
          "Product"
        ],
        "responses": {
          "200": {
            "description": "OK"
          }
        }
      }
    },
    "/api/Product/delete/{productId}": {
      "delete": {
        "tags": [
          "Product"
        ],
        "parameters": [
          {
            "name": "productId",
            "in": "path",
            "required": true,
            "schema": {
              "type": "integer",
              "format": "int32"
            }
          }
        ],
        "responses": {
          "200": {
            "description": "OK"
          }
        }
      }
    },
    "/api/Product/{productId}": {
      "get": {
        "tags": [
          "Product"
        ],
        "parameters": [
          {
            "name": "productId",
            "in": "path",
            "required": true,
            "schema": {
              "type": "integer",
              "format": "int32"
            }
          }
        ],
        "responses": {
          "200": {
            "description": "OK"
          }
        }
      }
    },
    "/api/Product/update/{productId}": {
      "put": {
        "tags": [
          "Product"
        ],
        "parameters": [
          {
            "name": "productId",
            "in": "path",
            "required": true,
            "schema": {
              "type": "integer",
              "format": "int32"
            }
          }
        ],
        "requestBody": {
          "content": {
            "multipart/form-data": {
              "schema": {
                "type": "object",
                "properties": {
                  "ProductId": {
                    "type": "integer",
                    "format": "int32"
                  },
                  "Name": {
                    "type": "string"
                  },
                  "Price": {
                    "type": "number",
                    "format": "double"
                  },
                  "ImageFile": {
                    "type": "string",
                    "format": "binary"
                  },
                  "Description": {
                    "type": "string"
                  },
                  "Quantity": {
                    "type": "integer",
                    "format": "int32"
                  },
                  "CategoryName": {
                    "type": "string"
                  },
                  "ImageUrl": {
                    "type": "string"
                  },
                  "NumberOfViewers": {
                    "type": "integer",
                    "format": "int32"
                  },
                  "VendorName": {
                    "type": "string"
                  }
                }
              },
              "encoding": {
                "ProductId": {
                  "style": "form"
                },
                "Name": {
                  "style": "form"
                },
                "Price": {
                  "style": "form"
                },
                "ImageFile": {
                  "style": "form"
                },
                "Description": {
                  "style": "form"
                },
                "Quantity": {
                  "style": "form"
                },
                "CategoryName": {
                  "style": "form"
                },
                "ImageUrl": {
                  "style": "form"
                },
                "NumberOfViewers": {
                  "style": "form"
                },
                "VendorName": {
                  "style": "form"
                }
              }
            }
          }
        },
        "responses": {
          "200": {
            "description": "OK"
          }
        }
      }
    },
    "/api/Product/track/{productName}": {
      "get": {
        "tags": [
          "Product"
        ],
        "parameters": [
          {
            "name": "productName",
            "in": "path",
            "required": true,
            "schema": {
              "type": "string"
            }
          }
        ],
        "responses": {
          "200": {
            "description": "OK"
          }
        }
      }
    },
    "/api/Product/names": {
      "get": {
        "tags": [
          "Product"
        ],
        "responses": {
          "200": {
            "description": "OK"
          }
        }
      }
    },
    "/api/RfreshToken/RefreshToken": {
      "post": {
        "tags": [
          "RfreshToken"
        ],
        "requestBody": {
          "content": {
            "application/json": {
              "schema": {
                "$ref": "#/components/schemas/RefreshTokenRequest"
              }
            },
            "text/json": {
              "schema": {
                "$ref": "#/components/schemas/RefreshTokenRequest"
              }
            },
            "application/*+json": {
              "schema": {
                "$ref": "#/components/schemas/RefreshTokenRequest"
              }
            }
          }
        },
        "responses": {
          "200": {
            "description": "OK"
          }
        }
      }
    },
    "/api/User/register": {
      "post": {
        "tags": [
          "User"
        ],
        "requestBody": {
          "content": {
            "application/json": {
              "schema": {
                "$ref": "#/components/schemas/UserDTO"
              }
            },
            "text/json": {
              "schema": {
                "$ref": "#/components/schemas/UserDTO"
              }
            },
            "application/*+json": {
              "schema": {
                "$ref": "#/components/schemas/UserDTO"
              }
            }
          }
        },
        "responses": {
          "200": {
            "description": "OK"
          }
        }
      }
    },
    "/api/User/login": {
      "post": {
        "tags": [
          "User"
        ],
        "requestBody": {
          "content": {
            "application/json": {
              "schema": {
                "$ref": "#/components/schemas/LoginDTO"
              }
            },
            "text/json": {
              "schema": {
                "$ref": "#/components/schemas/LoginDTO"
              }
            },
            "application/*+json": {
              "schema": {
                "$ref": "#/components/schemas/LoginDTO"
              }
            }
          }
        },
        "responses": {
          "200": {
            "description": "OK"
          }
        }
      }
    },
    "/api/User/logout": {
      "post": {
        "tags": [
          "User"
        ],
        "responses": {
          "200": {
            "description": "OK"
          }
        }
      }
    }
  },
  "components": {
    "schemas": {
      "GrantPermissionDto": {
        "type": "object",
        "properties": {
          "adminId": {
            "type": "integer",
            "format": "int32"
          },
          "vendorId": {
            "type": "integer",
            "format": "int32"
          },
          "permissionId": {
            "type": "integer",
            "format": "int32"
          }
        },
        "additionalProperties": false
      },
      "LoginDTO": {
        "type": "object",
        "properties": {
          "email": {
            "type": "string",
            "nullable": true
          },
          "password": {
            "type": "string",
            "nullable": true
          }
        },
        "additionalProperties": false
      },
      "RefreshTokenRequest": {
        "type": "object",
        "properties": {
          "token": {
            "type": "string",
            "nullable": true
          }
        },
        "additionalProperties": false
      },
      "UserDTO": {
        "type": "object",
        "properties": {
          "name": {
            "type": "string",
            "nullable": true
          },
          "email": {
            "type": "string",
            "nullable": true
          },
          "password": {
            "type": "string",
            "nullable": true
          },
          "role": {
            "type": "string",
            "nullable": true
          },
          "phone": {
            "type": "string",
            "nullable": true
          },
          "address": {
            "type": "string",
            "nullable": true
          }
        },
        "additionalProperties": false
      }
    },
    "securitySchemes": {
      "Bearer": {
        "type": "apiKey",
        "description": "Enter 'Bearer' [space] and then your valid token.\r\n\r\nExample: \"Bearer eyJ...\"",
        "name": "Authorization",
        "in": "header"
      }
    }
  },
  "security": [
    {
      "Bearer": [ ]
    }
  ]
}